syrupy/__init__.py
syrupy/assertion.py
syrupy/constants.py
syrupy/data.py
syrupy/exceptions.py
syrupy/extensions/__init__.py
syrupy/extensions/amber/__init__.py
syrupy/extensions/amber/serializer.py
syrupy/extensions/base.py
syrupy/extensions/image.py
syrupy/extensions/json/__init__.py
syrupy/extensions/single_file.py
syrupy/filters.py
syrupy/location.py
syrupy/matchers.py
syrupy/patches/__init__.py
syrupy/patches/pycharm_diff.py
syrupy/py.typed
syrupy/report.py
syrupy/session.py
syrupy/terminal.py
syrupy/types.py
syrupy/utils.py
syrupy-4.8.3.dist-info/LICENSE
syrupy-4.8.3.dist-info/METADATA
syrupy-4.8.3.dist-info/WHEEL
syrupy-4.8.3.dist-info/entry_points.txt
syrupy-4.8.3.dist-info/RECORD
