Metadata-Version: 2.1
Name: syrupy
Version: 4.8.3
Summary: Pytest Snapshot Test Utility
Home-page: https://github.com/syrupy-project/syrupy
License: Apache-2.0
Author: Noah Ulster
Requires-Python: >=3.8.1
Classifier: Development Status :: 5 - Production/Stable
Classifier: Framework :: Pytest
Classifier: Intended Audience :: Developers
Classifier: License :: OSI Approved :: Apache Software License
Classifier: Operating System :: OS Independent
Classifier: Programming Language :: Python :: 3
Classifier: Programming Language :: Python :: 3.9
Classifier: Programming Language :: Python :: 3.10
Classifier: Programming Language :: Python :: 3.11
Classifier: Programming Language :: Python :: 3.12
Classifier: Programming Language :: Python :: 3.13
Classifier: Programming Language :: Python :: 3.8
Classifier: Topic :: Software Development :: Libraries
Classifier: Topic :: Software Development :: Testing
Classifier: Topic :: Utilities
Requires-Dist: pytest (>=7.0.0,<9.0.0)
Project-URL: Repository, https://github.com/syrupy-project/syrupy
